chextra/__init__.py
chextra/py.typed
chextra-0.1.1.dist-info/WHEEL
chextra-0.1.1.dist-info/METADATA
chextra-0.1.1.dist-info/licenses/LICENSE
chextra-0.1.1.dist-info/RECORD
