Metadata-Version: 2.1
Name: chextra
Version: 0.1.1
Summary: Arm your library with a simple warning-call if users try to make use of uninstalled extras.
License: MIT
Keywords: extra,extras,warning,metadata
Author-email: Arne Caratti <arne.recknagel@hotmail.com>
Maintainer-email: Arne Caratti <arne.recknagel@hotmail.com>
Requires-Python: >=3.10
Classifier: Intended Audience :: Developers
Classifier: License :: OSI Approved :: MIT License
Classifier: Operating System :: POSIX :: Linux
Classifier: Programming Language :: Python :: 3.10
Classifier: Programming Language :: Python :: 3.11
Classifier: Typing :: Typed
Requires-Dist: packaging>=23.0
Project-URL: documentation, https://a-recknagel.github.io/chextra/
Project-URL: repository, https://github.com/a-recknagel/chextra
